[
  {
    "_id": "684db81a82c73fdf7136d92e",
    "nombre": "Juan Calizaya",
    "email": "juan@example.com",
    "contrasena": "123456",
    "tipo": "estudiante",
    "perfil": {
      "bio": "Dedicado al frontend.",
      "foto": "juan.jpg",
      "intereses": [
        "Programación",
        "Bases de Datos"
      ]
    }
  },
  {
    "_id": "684db81a82c73fdf7136d92f",
    "nombre": "Ana Ventura",
    "email": "ana@example.com",
    "contrasena": "ana123",
    "tipo": "estudiante",
    "perfil": {
      "bio": "Me gusta el desarrollo web.",
      "foto": "ana.jpg",
      "intereses": [
        "Web",
        "UX/UI"
      ]
    }
  },
  {
    "_id": "684db81a82c73fdf7136d930",
    "nombre": "Luis Torres",
    "email": "luis@example.com",
    "contrasena": "luis123",
    "tipo": "estudiante",
    "perfil": {
      "bio": "Apasionado por los datos.",
      "foto": "luis.jpg",
      "intereses": [
        "Data Science",
        "Python"
      ]
    }
  },
  {
    "_id": "684db81a82c73fdf7136d931",
    "nombre": "Admin General",
    "email": "admin@example.com",
    "contrasena": "admin1234",
    "tipo": "administrador"
  },
  {
    "_id": "123456",
    "nombre": "Usuario de Prueba",
    "email": "correo@mail.com",
    "contrasena": "123456",
    "tipo": "estudiante",
    "perfil": {
      "bio": "Usuario de prueba para posts.",
      "foto": "usuario.png",
      "intereses": []
    }
  }
]